AxionVueOpenAPI/__init__.py
AxionVueOpenAPI/axion_vue_device.py
AxionVueOpenAPI/listener.py
AxionVueOpenAPI/main.py
AxionVueOpenAPI/AxionVueApp/Azure.Core.dll
AxionVueOpenAPI/AxionVueApp/Azure.Storage.Blobs.dll
AxionVueOpenAPI/AxionVueApp/Azure.Storage.Common.dll
AxionVueOpenAPI/AxionVueApp/Camera.dll
AxionVueOpenAPI/AxionVueApp/Camera.pdb
AxionVueOpenAPI/AxionVueApp/CytoSmart.Logic.CellCounter.dll
AxionVueOpenAPI/AxionVueApp/CytoSmart.Logic.CellCounter.pdb
AxionVueOpenAPI/AxionVueApp/CytoSmart.Logic.Lux.dll
AxionVueOpenAPI/AxionVueApp/CytoSmart.Logic.Lux.pdb
AxionVueOpenAPI/AxionVueApp/CytoSmart.Logic.Omni.Common.dll
AxionVueOpenAPI/AxionVueApp/CytoSmart.Logic.Omni.Common.pdb
AxionVueOpenAPI/AxionVueApp/CytoSmart.Logic.Omni.RobotArm.dll
AxionVueOpenAPI/AxionVueApp/CytoSmart.Logic.Omni.RobotArm.pdb
AxionVueOpenAPI/AxionVueApp/CytoSmart.Logic.Omni.dll
AxionVueOpenAPI/AxionVueApp/CytoSmart.Logic.Omni.pdb
AxionVueOpenAPI/AxionVueApp/CytoSmart.Services.CellCounter.dll
AxionVueOpenAPI/AxionVueApp/CytoSmart.Services.CellCounter.pdb
AxionVueOpenAPI/AxionVueApp/CytoSmart.Services.Common.dll
AxionVueOpenAPI/AxionVueApp/CytoSmart.Services.Common.pdb
AxionVueOpenAPI/AxionVueApp/CytoSmart.Services.Lux.dll
AxionVueOpenAPI/AxionVueApp/CytoSmart.Services.Lux.pdb
AxionVueOpenAPI/AxionVueApp/CytoSmart.Services.Omni.dll
AxionVueOpenAPI/AxionVueApp/CytoSmart.Services.Omni.pdb
AxionVueOpenAPI/AxionVueApp/CytoSmartService.exe
AxionVueOpenAPI/AxionVueApp/CytoSmartService.exe.config
AxionVueOpenAPI/AxionVueApp/CytoSmartService.pdb
AxionVueOpenAPI/AxionVueApp/Device.Core.dll
AxionVueOpenAPI/AxionVueApp/Device.Core.pdb
AxionVueOpenAPI/AxionVueApp/Device.dll
AxionVueOpenAPI/AxionVueApp/Device.pdb
AxionVueOpenAPI/AxionVueApp/FirmwareUpdate_MD_VC140_v3_2_IDS.dll
AxionVueOpenAPI/AxionVueApp/GCBase_MD_VC140_v3_2_IDS.dll
AxionVueOpenAPI/AxionVueApp/GenApi_MD_VC140_v3_2_IDS.dll
AxionVueOpenAPI/AxionVueApp/ImageAlgorithms.dll
AxionVueOpenAPI/AxionVueApp/ImageProcessing.dll
AxionVueOpenAPI-1.3.1.dist-info/LICENSE
AxionVueOpenAPI-1.3.1.dist-info/METADATA
AxionVueOpenAPI-1.3.1.dist-info/WHEEL
AxionVueOpenAPI-1.3.1.dist-info/entry_points.txt
AxionVueOpenAPI-1.3.1.dist-info/top_level.txt
AxionVueOpenAPI-1.3.1.dist-info/RECORD
