Metadata-Version: 2.1
Name: AxionVueOpenAPI
Version: 1.3.1
Summary: This is a python wrapper for the Axion Vue windows app to use it headless
Home-page: https://github.com/cytosmart-bv/AxionVueOpenAPI
Author: Tom Nijhof
Keywords: AxionVueOpenAPI
Classifier: Development Status :: 4 - Beta
Classifier: Intended Audience :: Science/Research
Classifier: Operating System :: Microsoft
Classifier: Natural Language :: English
Classifier: Programming Language :: Python :: 3
Classifier: Programming Language :: Python :: 3 :: Only 
Classifier: Programming Language :: Python :: 3.6
Classifier: Programming Language :: Python :: 3.7
Classifier: Programming Language :: Python :: 3.8
Classifier: Programming Language :: Python :: 3.9
Classifier: Programming Language :: Python :: 3.10
Classifier: Topic :: Scientific/Engineering :: Bio-Informatics 
Classifier: Topic :: Scientific/Engineering :: Medical Science Apps.
License-File: LICENSE
Requires-Dist: pillow (<10,>=6.2.2)
Requires-Dist: requests (<3,>=2.24.0)
Requires-Dist: websocket-client (<2,>=0.57.0)
